{
  "kind": "collectionType",
  "collectionName": "merchants",
  "info": {
    "name": "Merchant",
    "description": "Đại lý"
  },
  "options": {
    "increments": true,
    "timestamps": true,
    "draftAndPublish": false
  },
  "attributes": {
    "name": {
      "type": "string",
      "required": true,
      "unique": true
    },
    "email": {
      "type": "email",
      "unique": true
    },
    "phoneNumber": {
      "type": "string",
      "unique": true,
      "required": true
    },
    "website": {
      "type": "string"
    },
    "zalo": {
      "type": "string"
    },
    "address": {
      "type": "string"
    },
    "note": {
      "type": "richtext"
    }
  }
}
